Metadata-Version: 1.0
Name: anngyan-prob
Version: 0.1
Summary: Gaussian and Binomial distributions
Home-page: UNKNOWN
Author: Anna Gasparyan
Author-email: gasparyan.2003.ag@gmail.com
License: UNKNOWN
Platform: UNKNOWN
